[{"userId":"uid_1773996228085_huwcqshmf","characterId":"86e47560-cc4d-48dc-a79f-3a7bf6a88289","id":"1775241196153","timestamp":1775241196153,"charId":"86e47560-cc4d-48dc-a79f-3a7bf6a88289","duration":146,"status":"connected","logs":[{"sender":"ai","content":"接电话。","timestamp":1775241049398,"ttsGroupTimestamp":1775241049398},{"sender":"user","content":"你想干嘛","timestamp":1775241065729},{"sender":"ai","content":"我想干嘛？","timestamp":1775241088941,"ttsGroupTimestamp":1775241088941},{"sender":"ai","content":"......呵。","timestamp":1775241088942,"ttsGroupTimestamp":1775241088941},{"sender":"ai","content":"你他妈现在给我说清楚。","timestamp":1775241088943,"ttsGroupTimestamp":1775241088941},{"sender":"ai","content":"陈叙......你跟他，到哪一步了？","timestamp":1775241088944,"ttsGroupTimestamp":1775241088941},{"sender":"ai","content":"他碰你了？","timestamp":1775241088945,"ttsGroupTimestamp":1775241088941},{"sender":"ai","content":"回答我！","timestamp":1775241088946,"ttsGroupTimestamp":1775241088941},{"sender":"ai","content":"沈薇！","timestamp":1775241088947,"ttsGroupTimestamp":1775241088941},{"sender":"user","content":"我没必要和你报备吧，你又不是我的谁？","timestamp":1775241130150},{"sender":"ai","content":"呵......我不是你的谁？","timestamp":1775241147638,"ttsGroupTimestamp":1775241147638},{"sender":"ai","content":"沈薇，你他妈再说一遍。","timestamp":1775241147639,"ttsGroupTimestamp":1775241147638},{"sender":"ai","content":"几个小时前你在我身下的时候，怎么不说我不是你的谁？","timestamp":1775241147640,"ttsGroupTimestamp":1775241147638},{"sender":"ai","content":"现在跟我撇清关系了？","timestamp":1775241147641,"ttsGroupTimestamp":1775241147638},{"sender":"ai","content":"你觉得老子会认？！","timestamp":1775241147642,"ttsGroupTimestamp":1775241147638},{"sender":"ai","content":"你开门。","timestamp":1775241147643,"ttsGroupTimestamp":1775241147638},{"sender":"ai","content":"我现在上去。","timestamp":1775241147644,"ttsGroupTimestamp":1775241147638},{"sender":"ai","content":"你当着我的面，跟陈叙打电话，我看他敢不敢过来！","timestamp":1775241147645,"ttsGroupTimestamp":1775241147638}],"isIncomingCall":true,"_id":3,"summary":"凌晨，顾峥因嫉妒而致电沈薇，激烈质问她与陈叙的关系进展。当沈薇试图撇清关系时，顾峥被激怒，提及数小时前两人间的亲密行为，并表示他将立刻上楼找她，要求她当面对质。"}]